<?xml version="1.0" encoding="UTF-8"?>
<objects serializationModel="Studio.02.02.00">
	<object class="AudioFile" id="{fafd4ff5-ae88-4ec1-853e-2f0dca1a3f69}">
		<property name="assetPath">
			<value>Weapons/AWDS_SR_Model_700P_340_Close_Single - Trimmed.wav</value>
		</property>
		<property name="frequencyInKHz">
			<value>8</value>
		</property>
		<property name="channelCount">
			<value>2</value>
		</property>
		<property name="length">
			<value>2.6048749999999998</value>
		</property>
		<relationship name="masterAssetFolder">
			<destination>{06e99160-eeb7-4fd9-939d-fe84f3b7d247}</destination>
		</relationship>
	</object>
</objects>
